{
  "AWSTemplateFormatVersion" : "2010-09-09",

  "Description" : "Networking Stack",

  "Metadata" : {
  },

  "Parameters" : {
    "Target" : {
      "Type" : "String"
    },
    "Stack" : {
      "Type" : "String"
    },
    "VPCCIDRBlock" : {
      "Type" : "String"
    },
    "PubSubCIDR1" : {
      "Type" : "String"
    },
    "PubSubCIDR2" : {
      "Type" : "String"
    }
  },

  "Mappings" : {
  },

  "Conditions" : {
  },

  "Resources" : {
    "VPC" : {
      "Type" : "AWS::EC2::VPC",
      "Properties" : {
        "CidrBlock" : { "Ref" : "VPCCIDRBlock" },
        "EnableDnsHostnames" : "true",
        "Tags" : [ { "Key" : "Name", "Value" : "slalom-aws-intro" } ]
      }
    },

    "PubSubnet1" : {
      "Type" : "AWS::EC2::Subnet",
      "Properties" : {
        "AvailabilityZone" : {
          "Fn::Select" : [ "0", { "Fn::GetAZs" : "" } ]

        },
        "CidrBlock" : { "Ref" : "PubSubCIDR1" },
        "MapPublicIpOnLaunch" : "true",
        "Tags" : [ { "Key" : "Name", "Value" : "slalom-aws-intro-pub1" } ],
        "VpcId" : { "Ref" : "VPC" }
      }
    },

    "PubSubnet2" : {
      "Type" : "AWS::EC2::Subnet",
      "Properties" : {
        "AvailabilityZone" : {
          "Fn::Select" : [ "1", { "Fn::GetAZs" : "" } ]

        },
        "CidrBlock" : { "Ref" : "PubSubCIDR2" },
        "MapPublicIpOnLaunch" : "true",
        "Tags" : [ { "Key" : "Name", "Value" : "slalom-aws-intro-pub2" } ],
        "VpcId" : { "Ref" : "VPC" }
      }
    },

    "IGW" : {
      "Type" : "AWS::EC2::InternetGateway",
      "Properties" : {
        "Tags" : [ { "Key" : "Name", "Value" : "slalom-aws-intro-igw" } ]
      }
    },

    "IGWAttachment" : {
      "Type" : "AWS::EC2::VPCGatewayAttachment",
      "Properties" : {
        "InternetGatewayId" : { "Ref" : "IGW" },
        "VpcId" : { "Ref" : "VPC" }
      }
    },

    "PubRouteTable1" : {
      "Type" : "AWS::EC2::RouteTable",
      "Properties" : {
        "VpcId" : { "Ref" : "VPC" },
        "Tags" : [ { "Key" : "Name", "Value" : "slalom-aws-intro-rtb1" } ]
      }
    },
    "PubRouteTable2" : {
      "Type" : "AWS::EC2::RouteTable",
      "Properties" : {
        "VpcId" : { "Ref" : "VPC" },
        "Tags" : [ { "Key" : "Name", "Value" : "slalom-aws-intro-rtb2" } ]
      }
    },

    "PubRtbAssoc1" : {
      "Type" : "AWS::EC2::SubnetRouteTableAssociation",
      "Properties" : {
        "RouteTableId" : { "Ref" : "PubRouteTable1" },
        "SubnetId" : { "Ref" : "PubSubnet1" }
      }
    },

    "PubRtbAssoc2" : {
      "Type" : "AWS::EC2::SubnetRouteTableAssociation",
      "Properties" : {
        "RouteTableId" : { "Ref" : "PubRouteTable2" },
        "SubnetId" : { "Ref" : "PubSubnet2" }
      }
    },

    "IGWRoutePub1" : {
      "Type" : "AWS::EC2::Route",
      "Properties" : {
        "DestinationCidrBlock" : "0.0.0.0/0",
        "GatewayId" : { "Ref" : "IGW" },
        "RouteTableId" : { "Ref" : "PubRouteTable1" }
      }
    },

    "IGWRoutePub2" : {
      "Type" : "AWS::EC2::Route",
      "Properties" : {
        "DestinationCidrBlock" : "0.0.0.0/0",
        "GatewayId" : { "Ref" : "IGW" },
        "RouteTableId" : { "Ref" : "PubRouteTable2" }
      }
    }
  },

  "Outputs" : {
    "VPCId" : {
      "Description" : "VPC ID",
      "Value" : { "Ref" : "VPC" },
      "Export" : { "Name" : {"Fn::Sub": "${AWS::StackName}-VPCID"}}
    },

    "PubSubnet1" : {
      "Description" : "Public Subnet 1",
      "Value" : { "Ref" : "PubSubnet1" },
      "Export" : { "Name" : {"Fn::Sub": "${AWS::StackName}-PubSubnet1"}}
    },

    "PubSubnet2" : {
      "Description" : "Public Subnet 2",
      "Value" : { "Ref" : "PubSubnet2" },
      "Export" : { "Name" : {"Fn::Sub": "${AWS::StackName}-PubSubnet2"}}
    }
  }
}















